globetrotter.py
setup.py
globetrotter.egg-info/PKG-INFO
globetrotter.egg-info/SOURCES.txt
globetrotter.egg-info/dependency_links.txt
globetrotter.egg-info/requires.txt
globetrotter.egg-info/top_level.txt