Metadata-Version: 1.0
Name: globetrotter
Version: 0.1.0
Summary: Approximate country and language name matching.
Home-page: http://bitbucket.org/larsyencken/globetrotter
Author: Lars Yencken
Author-email: lars@yencken.org
License: ISC
Platform: UNKNOWN
